setup.cfg
setup.py
distributions_Binomial_Gaussian/Binomialdistribution.py
distributions_Binomial_Gaussian/Gaussiandistribution.py
distributions_Binomial_Gaussian/Generaldistribution.py
distributions_Binomial_Gaussian/__init__.py
distributions_Binomial_Gaussian.egg-info/PKG-INFO
distributions_Binomial_Gaussian.egg-info/SOURCES.txt
distributions_Binomial_Gaussian.egg-info/dependency_links.txt
distributions_Binomial_Gaussian.egg-info/not-zip-safe
distributions_Binomial_Gaussian.egg-info/top_level.txt