Metadata-Version: 1.0
Name: distributions-Binomial-Gaussian
Version: 1.5
Summary: Gaussian distributions
Home-page: UNKNOWN
Author: Raveena Mathur
Author-email: raveenam@usc.edu
License: UNKNOWN
Platform: UNKNOWN
